LibvirtKVMBackup/__init__.py
LibvirtKVMBackup-1.0.dist-info/METADATA
LibvirtKVMBackup-1.0.dist-info/WHEEL
LibvirtKVMBackup-1.0.dist-info/top_level.txt
LibvirtKVMBackup-1.0.dist-info/RECORD
