Metadata-Version: 2.1
Name: LibvirtKVMBackup
Version: 1.0
Summary: Python module to backup Libvirt domains
Author-email: Stijn Rombouts <stijnrombouts@outlook.com>
Project-URL: Homepage, https://github.com/macOS-KVM/LibvirtKVMBackup
Project-URL: Bug Tracker, https://github.com/macOS-KVM/LibvirtKVMBackup/issues
Requires-Python: >=3.7
